{"type": "Feature", "id": 12510907, "properties": {"woe:id": 12510907, "woe:parent_id": 346112, "woe:name": "Jorge Henrich Arauz Airport", "woe:placetype": 14, "woe:placetype_name": "Airport", "woe:lang": "ENG", "iso:country": "BO", "meta:provider": ["geoplanet:7.3.1", "geoplanet:7.3.2", "geoplanet:7.4.0", "geoplanet:7.4.1", "geoplanet:7.5.1", "geoplanet:7.5.2", "geoplanet:7.6.0", "geoplanet:7.8.1", "geoplanet:7.9.0", "geoplanet:7.10.0", "geoplanet:8.0.0", "woeplanet:8.0.0"], "meta:indexed": "2020-08-20T20:52:05.317400", "woe:alias_ENG_V": ["TDD Airport", "TDD", "Jorge Henrich Arauz"], "meta:updated": "2020-08-22T02:50:41.908301", "woe:hierarchy": {"continent": 24865673, "country": 23424762, "town": 0, "planet": 1, "county": 55967772, "suburb": 0, "state": 2344803, "region": 0, "localadmin": 55967921}, "woe:timezone_id": 28350768, "woe:hash": "6t3gdycsc5zr", "woe:centroid": [-64.9161, -14.8156], "geom:latitude": -14.8156, "geom:longitude": -64.9161, "geom:hash": "6t3gdycsc5zr", "woe:latitude": -14.8156, "geom:centroid": [-64.9161, -14.8156], "woe:longitude": -64.9161, "woe:repo": "woeplanet-airport-bo"}, "geometry": {"coordinates": [-64.9161, -14.8156], "type": "Point"}}