{"type": "Feature", "id": 12524444, "properties": {"woe:id": 12524444, "woe:parent_id": 346104, "woe:name": "San Ramon Airport", "woe:placetype": 14, "woe:placetype_name": "Airport", "woe:lang": "ENG", "iso:country": "BO", "meta:provider": ["geoplanet:7.3.1", "geoplanet:7.3.2", "geoplanet:7.4.0", "geoplanet:7.4.1", "geoplanet:7.5.1", "geoplanet:7.5.2", "geoplanet:7.6.0", "geoplanet:7.8.1", "geoplanet:7.9.0", "geoplanet:7.10.0", "geoplanet:8.0.0", "woeplanet:8.0.0"], "meta:indexed": "2020-08-20T20:52:05.342737", "woe:alias_ENG_V": ["SRD Airport", "SRD"], "meta:updated": "2020-08-22T02:50:41.918566", "woe:hierarchy": {"continent": 24865673, "country": 23424762, "town": 0, "planet": 1, "county": 55967774, "suburb": 0, "state": 2344803, "region": 0, "localadmin": 55967928}, "woe:timezone_id": 28350768, "woe:hash": "6t9urtyghv3t", "woe:centroid": [-64.699997, -13.2833], "geom:latitude": -13.2833, "geom:longitude": -64.699997, "geom:hash": "6t9urtyghv3t", "woe:latitude": -13.2833, "geom:centroid": [-64.699997, -13.2833], "woe:longitude": -64.699997, "woe:repo": "woeplanet-airport-bo"}, "geometry": {"coordinates": [-64.699997, -13.2833], "type": "Point"}}